{
  "books": [
    {
      "id": 0,
      "authors": "Tom Rob Smith",
      "title": "Child 44",
      "noOfPages": 1000,
      "publisher": "Penguin",
      "lang": "en",
      "isbn10": 9780000000,
      "isbn13": "978-0000000000",
      "publicationDate": {
        "dd": "01",
        "mm": "01",
        "yyyy": "1900"
      }
    },
    {
      "id": 1,
      "authors": "Tom Rob Smith",
      "title": "The Secret Speech",
      "noOfPages": 1001,
      "publisher": "Penguin",
      "lang": "en",
      "isbn10": 9780000000,
      "isbn13": "978-0000000000",
      "publicationDate": {
        "dd": "01",
        "mm": "01",
        "yyyy": "1911"
      }
    },
    {
      "id": 2,
      "authors": "Tom Rob Smith",
      "title": "Agent 6",
      "noOfPages": 1002,
      "publisher": "Penguin",
      "lang": "en",
      "isbn10": 9780000000,
      "isbn13": "978-0000000000",
      "publicationDate": {
        "dd": "02",
        "mm": "02",
        "yyyy": "1922"
      }
    },
    {
      "id": 3,
      "authors": "Lee Child",
      "title": "Make Me",
      "noOfPages": 1003,
      "publisher": "Penguin",
      "lang": "en",
      "isbn10": 9780000000,
      "isbn13": "978-0000000000",
      "publicationDate": {
        "dd": "09",
        "mm": "11",
        "yyyy": "1999"
      }
    },
    {
      "id": 4,
      "authors": "Lee Child",
      "title": "Past Tense",
      "noOfPages": 400,
      "publisher": "Penguin",
      "lang": "en",
      "isbn10": 0,
      "isbn13": "978-0000000000",
      "publicationDate": {
        "dd": "04",
        "mm": "04",
        "yyyy": "1944"
      }
    },
    {
      "id": 5,
      "authors": "Roald Dahl",
      "title": "BFG",
      "noOfPages": 1000,
      "publisher": "Penguin",
      "lang": "en",
      "isbn10": 0,
      "isbn13": "978-0000000000",
      "publicationDate": {
        "dd": "05",
        "mm": "05",
        "yyyy": "1955"
      }
    },
    {
      "id": 6,
      "authors": "Roald Dahl",
      "title": "Fantastic Mr Fox",
      "noOfPages": 666,
      "publisher": "Penguin",
      "lang": "En",
      "isbn10": 9780000000,
      "isbn13": "978-0000000000",
      "publicationDate": {
        "dd": "06",
        "mm": "06",
        "yyyy": "1966"
      }
    }
  ]
}